jps_systemctl_utils/__init__.py
jps_systemctl_utils/constants.py
jps_systemctl_utils/logging_helper.py
jps_systemctl_utils/processor.py
jps_systemctl_utils/report_writer.py
jps_systemctl_utils/restart_services.py
jps_systemctl_utils-0.3.0.dist-info/licenses/LICENSE
jps_systemctl_utils-0.3.0.dist-info/METADATA
jps_systemctl_utils-0.3.0.dist-info/WHEEL
jps_systemctl_utils-0.3.0.dist-info/entry_points.txt
jps_systemctl_utils-0.3.0.dist-info/top_level.txt
jps_systemctl_utils-0.3.0.dist-info/RECORD
